sumeh_dq/__init__.py
sumeh_dq/sumeh_dq.py
sumeh_dq-0.1.1.dist-info/AUTHORS.md
sumeh_dq-0.1.1.dist-info/LICENSE
sumeh_dq-0.1.1.dist-info/METADATA
sumeh_dq-0.1.1.dist-info/WHEEL
sumeh_dq-0.1.1.dist-info/top_level.txt
sumeh_dq-0.1.1.dist-info/RECORD
