Metadata-Version: 2.1
Name: sumeh_dq
Version: 0.1.1
Summary: Sumeh is a project designed to extend the functionality of the Cuallee library by enabling the use of configuration
Author-email: Demetrius Albuquerque <demetrius.albuquerque@yahoo.com.br>
Maintainer-email: Demetrius Albuquerque <demetrius.albuquerque@yahoo.com.br>
License: Apache license
Project-URL: bugs, https://github.com/maltzsama/sumeh_dq/issues
Project-URL: changelog, https://github.com/maltzsama/sumeh_dq/blob/master/changelog.md
Project-URL: homepage, https://github.com/maltzsama/sumeh_dq
License-File: LICENSE
License-File: AUTHORS.md
Requires-Dist: cuallee >=0.14.1
Requires-Dist: python-dateutil
Provides-Extra: aws
Requires-Dist: boto3 ; extra == 'aws'
Provides-Extra: bigquery
Requires-Dist: google-cloud-bigquery ; extra == 'bigquery'
Provides-Extra: dev
Requires-Dist: coverage ; extra == 'dev'
Requires-Dist: mypy ; extra == 'dev'
Requires-Dist: pytest ; extra == 'dev'
Requires-Dist: ruff ; extra == 'dev'
Provides-Extra: mysql
Requires-Dist: mysql-connector-python ; extra == 'mysql'
Requires-Dist: pandas ; extra == 'mysql'
Provides-Extra: postgresql
Requires-Dist: psycopg2-binary ; extra == 'postgresql'
Requires-Dist: pandas ; extra == 'postgresql'
